logic_server/__init__.py
logic_server/cli/__init__.py
logic_server/cli/main.py
logic_server/core/__init__.py
logic_server/core/formatting.py
logic_server/core/mqi_solver.py
logic_server/core/prolog_pool.py
logic_server/core/schema.py
logic_server/core/session.py
logic_server/core/solver.py
logic_server/llm/__init__.py
logic_server/llm/clients.py
logic_server/mcp/__init__.py
logic_server/mcp/server.py
logic_server/mcp/stateful.py
prolog_logic_server-0.1.5.data/scripts/logic_server
prolog_logic_server-0.1.5.data/scripts/logic_server_mcp
prolog_logic_server-0.1.5.dist-info/licenses/LICENSE
prolog_logic_server-0.1.5.dist-info/METADATA
prolog_logic_server-0.1.5.dist-info/WHEEL
prolog_logic_server-0.1.5.dist-info/entry_points.txt
prolog_logic_server-0.1.5.dist-info/top_level.txt
prolog_logic_server-0.1.5.dist-info/RECORD
