Metadata-Version: 2.4
Name: prolog-logic-server
Version: 0.1.5
Summary: Constraint-based logic reasoning server with MCP integration for Claude Desktop and Claude Code
Author-email: Brian Guarraci <brian@ops5.com>
License-Expression: MIT
Project-URL: Homepage, https://github.com/briangu/prolog-logic-server
Project-URL: Repository, https://github.com/briangu/prolog-logic-server
Project-URL: Documentation, https://github.com/briangu/prolog-logic-server#readme
Project-URL: Bug Tracker, https://github.com/briangu/prolog-logic-server/issues
Keywords: logic,reasoning,prolog,mcp,claude,llm,constraint-solving
Classifier: Development Status :: 3 - Alpha
Classifier: Intended Audience :: Developers
Classifier: Intended Audience :: Science/Research
Classifier: Programming Language :: Python :: 3
Classifier: Programming Language :: Python :: 3.10
Classifier: Programming Language :: Python :: 3.11
Classifier: Programming Language :: Python :: 3.12
Classifier: Programming Language :: Python :: 3.13
Classifier: Topic :: Scientific/Engineering :: Artificial Intelligence
Classifier: Topic :: Software Development :: Libraries :: Python Modules
Classifier: Topic :: Scientific/Engineering :: Information Analysis
Classifier: Framework :: AsyncIO
Requires-Python: >=3.10
License-File: LICENSE
Requires-Dist: requests>=2.31.0
Requires-Dist: openai>=1.0.0
Requires-Dist: mcp>=0.1.0
Requires-Dist: jsonschema>=4.21.1
Requires-Dist: janus-swi>=1.5.0
Provides-Extra: dev
Requires-Dist: pytest>=7.0.0; extra == "dev"
Requires-Dist: pytest-cov>=4.0.0; extra == "dev"
Requires-Dist: black>=23.0.0; extra == "dev"
Requires-Dist: ruff>=0.1.0; extra == "dev"
Dynamic: license-file
